llama_index/py.typed
llama_index/indices/managed/lancedb/__init__.py
llama_index/indices/managed/lancedb/base.py
llama_index/indices/managed/lancedb/query_engine.py
llama_index/indices/managed/lancedb/retriever.py
llama_index/indices/managed/lancedb/utils.py
llama_index_vector_stores_lancedb_multimodal-0.1.0.dist-info/METADATA
llama_index_vector_stores_lancedb_multimodal-0.1.0.dist-info/WHEEL
llama_index_vector_stores_lancedb_multimodal-0.1.0.dist-info/licenses/LICENSE
llama_index_vector_stores_lancedb_multimodal-0.1.0.dist-info/RECORD
