Metadata-Version: 2.4
Name: llama-index-vector-stores-lancedb-multimodal
Version: 0.1.0
Summary: LlamaIndex x LanceDB MultiModal AI Lakehouse
Author-email: Clelia Astra Bertelli <clelia@runllama.ai>
License-Expression: MIT
License-File: LICENSE
Requires-Python: <4.0,>=3.9
Requires-Dist: lancedb<1,>=0.24.0
Requires-Dist: llama-index-core<0.13,>=0.12.44
Requires-Dist: open-clip-torch<3,>=2.32.0
Requires-Dist: polars<2,>=1.31.0
Requires-Dist: pyarrow<21,>=20.0.0
Requires-Dist: pylance<1,>=0.30.0
Requires-Dist: sentence-transformers<6,>=5.0.0
Requires-Dist: tantivy<1,>=0.24.0
